ascheck/__init__.py
ascheck/ascheck.py
ascheck-0.0.3.2.data/scripts/ascheck
ascheck_core/__init__.py
ascheck_core/ascheck_core.py
core/__init__.py
core/ascheck.py
ascheck-0.0.3.2.dist-info/METADATA
ascheck-0.0.3.2.dist-info/WHEEL
ascheck-0.0.3.2.dist-info/top_level.txt
ascheck-0.0.3.2.dist-info/RECORD
