Metadata-Version: 2.1
Name: ascheck
Version: 0.0.3.2
Summary: A package to perform image analysis on archaeological tools.
Home-page: https://github.com/StijnDebackere/AScheck
Author: Stijn Debackere
Author-email: debackere@strw.leidenuniv.nl
License: UNKNOWN
Platform: UNKNOWN
Classifier: Programming Language :: Python :: 3
Classifier: License :: OSI Approved :: MIT License
Classifier: Operating System :: OS Independent
Requires-Python: >=3.6
Requires-Dist: opencv-python (>=4.2.0)
Requires-Dist: numpy
Requires-Dist: matplotlib (>=2.0.0)
Requires-Dist: scipy
